dpkit/api/__init__.py
dpkit/api/__main__.py
dpkit/api/app.py
dpkit/api/main.py
dpkit/api/models.py
dpkit/api/store.py
dpkit/api/version.py
dpkit/api/server/__init__.py
dpkit/api/server/analysis.py
dpkit/api/server/auth.py
dpkit/api/server/fileset.py
dpkit/api/server/module.py
dpkit/api/storage/__init__.py
dpkit/api/storage/file.py
dpkit_api-0.1.2.dist-info/LICENSE
dpkit_api-0.1.2.dist-info/METADATA
dpkit_api-0.1.2.dist-info/NOTICE
dpkit_api-0.1.2.dist-info/WHEEL
dpkit_api-0.1.2.dist-info/top_level.txt
dpkit_api-0.1.2.dist-info/RECORD
